Metadata-Version: 1.1
Name: regionskate
Version: 1.0.0
Summary: A fast sparse algorithm for spatial regionalization.
Home-page: https://github.com/ljwolf/regionskate
Author: Levi John Wolf
Author-email: levi.john.wolf@gmail.com
License: ISC
Platform: UNKNOWN
Classifier: License :: OSI Approved :: MIT License
Classifier: Programming Language :: Python
Classifier: Programming Language :: Python :: 3
Classifier: Programming Language :: Python :: 3.6
Classifier: Programming Language :: Python :: Implementation :: CPython
